LICENSE
MANIFEST.in
README.md
setup.py
pyPayokAPI/__init__.py
pyPayokAPI/api.py
pyPayokAPI/payok_types.py
pyPayokAPI/tests.py
pyPayokAPI/version.py
pyPayokAPI.egg-info/PKG-INFO
pyPayokAPI.egg-info/SOURCES.txt
pyPayokAPI.egg-info/dependency_links.txt
pyPayokAPI.egg-info/top_level.txt