Metadata-Version: 2.1
Name: pyPayokAPI
Version: 0.0.3
Summary: Python implementation of Payok.io (https://payok.io/) pubilc API
Home-page: https://github.com/Badiboy/pyPayokAPI
Author: Badiboy
License: MIT license
Keywords: Payok Pay API
Classifier: Development Status :: 3 - Alpha
Classifier: Programming Language :: Python :: 3
Classifier: License :: OSI Approved :: MIT License
Requires: requests
Requires: hashlib
Requires: urllib
License-File: LICENSE
